en_core_web_sm/__init__.py
en_core_web_sm/meta.json
en_core_web_sm/en_core_web_sm-2.3.1/accuracy.json
en_core_web_sm/en_core_web_sm-2.3.1/meta.json
en_core_web_sm/en_core_web_sm-2.3.1/tokenizer
en_core_web_sm/en_core_web_sm-2.3.1/ner/cfg
en_core_web_sm/en_core_web_sm-2.3.1/ner/model
en_core_web_sm/en_core_web_sm-2.3.1/ner/moves
en_core_web_sm/en_core_web_sm-2.3.1/parser/cfg
en_core_web_sm/en_core_web_sm-2.3.1/parser/model
en_core_web_sm/en_core_web_sm-2.3.1/parser/moves
en_core_web_sm/en_core_web_sm-2.3.1/tagger/cfg
en_core_web_sm/en_core_web_sm-2.3.1/tagger/model
en_core_web_sm/en_core_web_sm-2.3.1/tagger/tag_map
en_core_web_sm/en_core_web_sm-2.3.1/vocab/key2row
en_core_web_sm/en_core_web_sm-2.3.1/vocab/lookups.bin
en_core_web_sm/en_core_web_sm-2.3.1/vocab/lookups_extra.bin
en_core_web_sm/en_core_web_sm-2.3.1/vocab/strings.json
en_core_web_sm/en_core_web_sm-2.3.1/vocab/vectors
dataqa_nlp_models-2.3.1.dist-info/METADATA
dataqa_nlp_models-2.3.1.dist-info/WHEEL
dataqa_nlp_models-2.3.1.dist-info/top_level.txt
dataqa_nlp_models-2.3.1.dist-info/RECORD
